PyBetStoric/__init__.py
PyBetStoric/bacara.py
PyBetStoric/base_game.py
PyBetStoric/client.py
PyBetStoric/config.py
PyBetStoric/crash.py
PyBetStoric/game_shows.py
PyBetStoric/games.py
PyBetStoric/generic_client.py
PyBetStoric/jogos_asiaticos.py
PyBetStoric/jogos_brasileiros.py
PyBetStoric/license.py
PyBetStoric/roleta.py
PyBetStoric/session.py
pybetstoric-1.0.2.dist-info/licenses/LICENSE
pybetstoric-1.0.2.dist-info/METADATA
pybetstoric-1.0.2.dist-info/WHEEL
pybetstoric-1.0.2.dist-info/top_level.txt
pybetstoric-1.0.2.dist-info/RECORD
