Metadata-Version: 2.4
Name: PyBetStoric
Version: 1.0.2
Summary: Biblioteca Python para acessar dados históricos de jogos da Pragmatic Play Live
Author: andre.melol
Author-email: amelo171710@gmail.com
License: MIT
Project-URL: Documentation, https://github.com/PyBetStoric/PyBetStoric/blob/main/README.md
Project-URL: Source, https://github.com/PyBetStoric/PyBetStoric
Project-URL: Tracker, https://github.com/PyBetStoric/PyBetStoric/issues
Keywords: pragmatic-play,live-casino,historical-data,gambling-data,casino-games,roulette,baccarat,blackjack,game-shows,crash-games,dragon-tiger,andar-bahar,sic-bo,spaceman,crazy-time,sweet-bonanza,monopoly-live,mega-roulette,speed-baccarat,lightning-roulette,brazilian-games,asian-games,casino-analytics,betting-history,live-dealer,casino-api
Classifier: Development Status :: 5 - Production/Stable
Classifier: Intended Audience :: Developers
Classifier: License :: OSI Approved :: MIT License
Classifier: Operating System :: OS Independent
Classifier: Programming Language :: Python :: 3
Classifier: Programming Language :: Python :: 3.7
Classifier: Programming Language :: Python :: 3.8
Classifier: Programming Language :: Python :: 3.9
Classifier: Programming Language :: Python :: 3.10
Classifier: Programming Language :: Python :: 3.11
Classifier: Programming Language :: Python :: 3.12
Classifier: Topic :: Software Development :: Libraries :: Python Modules
Classifier: Topic :: Games/Entertainment
Requires-Python: >=3.7
License-File: LICENSE
Requires-Dist: requests
Dynamic: author
Dynamic: author-email
Dynamic: classifier
Dynamic: description
Dynamic: description-content-type
Dynamic: keywords
Dynamic: license
Dynamic: license-file
Dynamic: project-url
Dynamic: requires-dist
Dynamic: requires-python
Dynamic: summary
